BoostAIO/__init__.py
boostaio-0.1.0.dist-info/licenses/LICENSE
boostaio-0.1.0.dist-info/METADATA
boostaio-0.1.0.dist-info/WHEEL
boostaio-0.1.0.dist-info/top_level.txt
boostaio-0.1.0.dist-info/RECORD
