Metadata-Version: 2.4
Name: boostaio
Version: 0.1.0
Summary: Python bindings for the BoostAIO C++ HTTP client library
Author: Alex
Author-email: Alex <alex_help_desk@exdonuts.com>
License: MIT
Keywords: http,bindings,boost,aio,networking
Platform: any
Classifier: Programming Language :: Python :: 3
Classifier: License :: OSI Approved :: MIT License
Classifier: Operating System :: POSIX :: Linux
Classifier: Operating System :: MacOS
Requires-Python: >=3.7
License-File: LICENSE
Dynamic: license-file
